Metadata-Version: 1.0
Name: Bi-Ga-distributions
Version: 0.1
Summary: Gaussianand Binomial distributions
Home-page: UNKNOWN
Author: Lamia Hasan Mohammed
Author-email: lamiahasan4@gmail.com
License: UNKNOWN
Platform: UNKNOWN
